{
  "openapi": "3.0.1",
  "info": {
    "title": "CloudAlerts",
    "version": "1.0.0"
  },
  "servers": [
    {
      "url": "https://alerts.xignite.com"
    }
  ],
  "paths": {
    "/xAlerts/CreateAlert.{formatter}": {
      "get": {
        "tags": [
          "CloudAlerts"
        ],
        "parameters": [
          {
            "name": "IdentifierType",
            "in": "query",
            "schema": {
              "type": "string"
            }
          },
          {
            "name": "Identifier",
            "in": "query",
            "schema": {
              "type": "string"
            }
          },
          {
            "name": "API",
            "in": "query",
            "schema": {
              "type": "string"
            }
          },
          {
            "name": "Condition",
            "in": "query",
            "schema": {
              "type": "string"
            }
          },
          {
            "name": "Reset",
            "in": "query",
            "schema": {
              "type": "string"
            }
          },
          {
            "name": "StartDate",
            "in": "query",
            "schema": {
              "type": "string"
            }
          },
          {
            "name": "EndDate",
            "in": "query",
            "schema": {
              "type": "string"
            }
          },
          {
            "name": "CallbackURL",
            "in": "query",
            "schema": {
              "type": "string"
            }
          },
          {
            "name": "formatter",
            "in": "path",
            "required": true,
            "schema": {
              "type": "string"
            }
          }
        ],
        "responses": {
          "200": {
            "description": "Success",
            "content": {
              "application/json": {
                "schema": {
                  "$ref": "#/components/schemas/Alert"
                }
              },
              "text/json": {
                "schema": {
                  "$ref": "#/components/schemas/Alert"
                }
              },
              "application/xml": {
                "schema": {
                  "$ref": "#/components/schemas/Alert"
                }
              },
              "text/xml": {
                "schema": {
                  "$ref": "#/components/schemas/Alert"
                }
              },
              "text/csv": {
                "schema": {
                  "$ref": "#/components/schemas/Alert"
                }
              }
            }
          }
        }
      }
    },
    "/xAlerts/DeleteAlerts.{formatter}": {
      "get": {
        "tags": [
          "CloudAlerts"
        ],
        "parameters": [
          {
            "name": "AlertIdentifiers",
            "in": "query",
            "schema": {
              "type": "string"
            }
          },
          {
            "name": "formatter",
            "in": "path",
            "required": true,
            "schema": {
              "type": "string"
            }
          }
        ],
        "responses": {
          "200": {
            "description": "Success",
            "content": {
              "application/json": {
                "schema": {
                  "type": "array",
                  "items": {
                    "$ref": "#/components/schemas/Alert"
                  }
                }
              },
              "text/json": {
                "schema": {
                  "type": "array",
                  "items": {
                    "$ref": "#/components/schemas/Alert"
                  }
                }
              },
              "application/xml": {
                "schema": {
                  "type": "array",
                  "items": {
                    "$ref": "#/components/schemas/Alert"
                  }
                }
              },
              "text/xml": {
                "schema": {
                  "type": "array",
                  "items": {
                    "$ref": "#/components/schemas/Alert"
                  }
                }
              },
              "text/csv": {
                "schema": {
                  "type": "array",
                  "items": {
                    "$ref": "#/components/schemas/Alert"
                  }
                }
              }
            }
          }
        }
      }
    },
    "/xAlerts/SearchAlerts.{formatter}": {
      "get": {
        "tags": [
          "CloudAlerts"
        ],
        "parameters": [
          {
            "name": "Pattern",
            "in": "query",
            "schema": {
              "type": "string"
            }
          },
          {
            "name": "formatter",
            "in": "path",
            "required": true,
            "schema": {
              "type": "string"
            }
          }
        ],
        "responses": {
          "200": {
            "description": "Success",
            "content": {
              "application/json": {
                "schema": {
                  "type": "array",
                  "items": {
                    "$ref": "#/components/schemas/Alert"
                  }
                }
              },
              "text/json": {
                "schema": {
                  "type": "array",
                  "items": {
                    "$ref": "#/components/schemas/Alert"
                  }
                }
              },
              "application/xml": {
                "schema": {
                  "type": "array",
                  "items": {
                    "$ref": "#/components/schemas/Alert"
                  }
                }
              },
              "text/xml": {
                "schema": {
                  "type": "array",
                  "items": {
                    "$ref": "#/components/schemas/Alert"
                  }
                }
              },
              "text/csv": {
                "schema": {
                  "type": "array",
                  "items": {
                    "$ref": "#/components/schemas/Alert"
                  }
                }
              }
            }
          }
        }
      }
    }
  },
  "components": {
    "schemas": {
      "OutcomeTypes": {
        "enum": [
          "Success",
          "SystemError",
          "RequestError",
          "RegistrationError"
        ],
        "type": "string"
      },
      "Common": {
        "type": "object",
        "properties": {
          "Outcome": {
            "allOf": [
              {
                "$ref": "#/components/schemas/OutcomeTypes"
              }
            ]
          },
          "Message": {
            "type": "string",
            "nullable": true
          },
          "Identity": {
            "type": "string",
            "nullable": true
          },
          "Delay": {
            "type": "number",
            "format": "double"
          }
        },
        "additionalProperties": false
      },
      "Alert": {
        "type": "object",
        "allOf": [
          {
            "$ref": "#/components/schemas/Common"
          }
        ],
        "properties": {
          "AlertIdentifier": {
            "type": "string",
            "nullable": true
          },
          "Status": {
            "type": "string",
            "nullable": true
          },
          "IdentifierType": {
            "type": "string",
            "nullable": true
          },
          "Identifier": {
            "type": "string",
            "nullable": true
          },
          "API": {
            "type": "string",
            "nullable": true
          },
          "Condition": {
            "type": "string",
            "nullable": true
          },
          "Reset": {
            "type": "string",
            "nullable": true
          },
          "CallbackURL": {
            "type": "string",
            "nullable": true
          },
          "StartDate": {
            "type": "string",
            "nullable": true
          },
          "LastTriggered": {
            "type": "string",
            "nullable": true
          },
          "EndDate": {
            "type": "string",
            "nullable": true
          }
        },
        "additionalProperties": false
      }
    },
    "securitySchemes": {
      "basic": {
        "type": "apiKey",
        "description": "Token for your account.",
        "name": "_token",
        "in": "query"
      }
    }
  },
  "security": [
    {
      "basic": [ ]
    }
  ]
}